{
  "type": "interest_by_region",
  "keyword": "Margarine",
  "start": "2020-01-01",
  "end": "2024-12-31",
  "geo": "DE",
  "resolution": "REGION",
  "rows": [
    {
      "geoName": "Baden-Württemberg",
      "geoCode": "DE-BW",
      "interest": 75
    },
    {
      "geoName": "Bayern",
      "geoCode": "DE-BY",
      "interest": 65
    },
    {
      "geoName": "Berlin",
      "geoCode": "DE-BE",
      "interest": 73
    },
    {
      "geoName": "Brandenburg",
      "geoCode": "DE-BB",
      "interest": 75
    },
    {
      "geoName": "Bremen",
      "geoCode": "DE-HB",
      "interest": 93
    },
    {
      "geoName": "Hamburg",
      "geoCode": "DE-HH",
      "interest": 79
    },
    {
      "geoName": "Hessen",
      "geoCode": "DE-HE",
      "interest": 70
    },
    {
      "geoName": "Mecklenburg-Vorpommern",
      "geoCode": "DE-MV",
      "interest": 76
    },
    {
      "geoName": "Niedersachsen",
      "geoCode": "DE-NI",
      "interest": 95
    },
    {
      "geoName": "Nordrhein-Westfalen",
      "geoCode": "DE-NW",
      "interest": 94
    },
    {
      "geoName": "Rheinland-Pfalz",
      "geoCode": "DE-RP",
      "interest": 79
    },
    {
      "geoName": "Saarland",
      "geoCode": "DE-SL",
      "interest": 81
    },
    {
      "geoName": "Sachsen",
      "geoCode": "DE-SN",
      "interest": 75
    },
    {
      "geoName": "Sachsen-Anhalt",
      "geoCode": "DE-ST",
      "interest": 74
    },
    {
      "geoName": "Schleswig-Holstein",
      "geoCode": "DE-SH",
      "interest": 100
    },
    {
      "geoName": "Thüringen",
      "geoCode": "DE-TH",
      "interest": 71
    }
  ]
}